README.md
setup.cfg
setup.py
superior6564/__init__.py
superior6564/app.py
superior6564/required_pack.py
superior6564/web.py
superior6564.egg-info/PKG-INFO
superior6564.egg-info/SOURCES.txt
superior6564.egg-info/dependency_links.txt
superior6564.egg-info/top_level.txt