Metadata-Version: 2.1
Name: superior6564
Version: 0.3.2
Summary: Before using you need to run: from superior6564 import required_pack; required_pack.install()
Home-page: https://github.com/Superior-GitHub/Superior6564
Author: Superior_6564
Author-email: vip.klochayil@gmail.com
License: Apache License, Version 2.0, see LICENSE file
Download-URL: https://github.com/Superior-GitHub/Superior6564/archive/refs/heads/main.zip
Platform: UNKNOWN
Classifier: License :: OSI Approved :: Apache Software License
Classifier: Intended Audience :: End Users/Desktop
Classifier: Intended Audience :: Developers
Classifier: Programming Language :: Python
Classifier: Programming Language :: Python :: 3.7
Classifier: Programming Language :: Python :: 3.8
Classifier: Programming Language :: Python :: 3.9
Classifier: Programming Language :: Python :: 3.10
